turkiye_son_depremler/__init__.py
turkiye_son_depremler-0.3.2.dist-info/LICENSE
turkiye_son_depremler-0.3.2.dist-info/METADATA
turkiye_son_depremler-0.3.2.dist-info/WHEEL
turkiye_son_depremler-0.3.2.dist-info/top_level.txt
turkiye_son_depremler-0.3.2.dist-info/RECORD
